{
  "id": "MAP_CASTELIA_CITY_CASTELIA_GYM",
  "name": "CasteliaCity_CasteliaGym",
  "layout": "LAYOUT_CASTELIA_CITY_CASTELIA_GYM",
  "music": "MUS_BW_GYM",
  "region_map_section": "MAPSEC_CASTELIA_CITY",
  "requires_flash": false,
  "weather": "WEATHER_NONE",
  "map_type": "MAP_TYPE_INDOOR",
  "allow_cycling": false,
  "allow_escaping": false,
  "allow_running": true,
  "show_map_name": false,
  "battle_scene": "MAP_BATTLE_SCENE_GYM",
  "connections": null,
  "object_events": [
    {
      "local_id": "LOCALID_CCCG_BURGH",
      "graphics_id": "OBJ_EVENT_GFX_BURGH",
      "x": 16,
      "y": 1,
      "elevation": 0,
      "movement_type": "MOVEMENT_TYPE_FACE_DOWN",
      "movement_range_x": 0,
      "movement_range_y": 0,
      "trainer_type": "TRAINER_TYPE_NONE",
      "trainer_sight_or_berry_tree_id": "0",
      "script": "CasteliaCity_CasteliaGym_EventScript_Battle_Burgh",
      "flag": "0"
    },
    {
      "local_id": "LOCALID_CCCG_RECEPTIONIST",
      "graphics_id": "OBJ_EVENT_GFX_GYM_RECEPTIONIST",
      "x": 18,
      "y": 36,
      "elevation": 0,
      "movement_type": "MOVEMENT_TYPE_FACE_DOWN",
      "movement_range_x": 0,
      "movement_range_y": 0,
      "trainer_type": "TRAINER_TYPE_NONE",
      "trainer_sight_or_berry_tree_id": "0",
      "script": "CasteliaCity_CasteliaGym_Eventscript_GymReceptionist",
      "flag": "0"
    },
    {
      "graphics_id": "OBJ_EVENT_GFX_PEIRRO",
      "x": 24,
      "y": 25,
      "elevation": 0,
      "movement_type": "MOVEMENT_TYPE_FACE_DOWN",
      "movement_range_x": 0,
      "movement_range_y": 0,
      "trainer_type": "TRAINER_TYPE_NORMAL",
      "trainer_sight_or_berry_tree_id": "3",
      "script": "CasteliaCity_CasteliaGym_EventScript_Battle_Harlequin_1",
      "flag": "0"
    },
    {
      "local_id": "LOCALID_CCCG_HARLEQUIN_1",
      "graphics_id": "OBJ_EVENT_GFX_PEIRRO",
      "x": 22,
      "y": 20,
      "elevation": 0,
      "movement_type": "MOVEMENT_TYPE_FACE_DOWN",
      "movement_range_x": 0,
      "movement_range_y": 0,
      "trainer_type": "TRAINER_TYPE_NONE",
      "trainer_sight_or_berry_tree_id": "0",
      "script": "CasteliaCity_CasteliaGym_EventScript_Harlequin_2",
      "flag": "FLAG_TEMP_11"
    },
    {
      "local_id": "LOCALID_CCCG_HARLEQUIN_2",
      "graphics_id": "OBJ_EVENT_GFX_PEIRRO",
      "x": 4,
      "y": 23,
      "elevation": 0,
      "movement_type": "MOVEMENT_TYPE_FACE_DOWN",
      "movement_range_x": 0,
      "movement_range_y": 0,
      "trainer_type": "TRAINER_TYPE_NONE",
      "trainer_sight_or_berry_tree_id": "0",
      "script": "CasteliaCity_CasteliaGym_EventScript_Harlequin_3",
      "flag": "FLAG_TEMP_12"
    },
    {
      "graphics_id": "OBJ_EVENT_GFX_PEIRRO",
      "x": 9,
      "y": 16,
      "elevation": 0,
      "movement_type": "MOVEMENT_TYPE_FACE_RIGHT",
      "movement_range_x": 0,
      "movement_range_y": 0,
      "trainer_type": "TRAINER_TYPE_NORMAL",
      "trainer_sight_or_berry_tree_id": "2",
      "script": "CasteliaCity_CasteliaGym_EventScript_Battle_Harlequin_4",
      "flag": "0"
    }
  ],
  "warp_events": [
    {
      "x": 15,
      "y": 38,
      "elevation": 0,
      "dest_map": "MAP_CASTELIA_CITY_GYM_STREET",
      "dest_warp_id": "17"
    },
    {
      "x": 16,
      "y": 38,
      "elevation": 0,
      "dest_map": "MAP_CASTELIA_CITY_GYM_STREET",
      "dest_warp_id": "17"
    },
    {
      "x": 17,
      "y": 38,
      "elevation": 0,
      "dest_map": "MAP_CASTELIA_CITY_GYM_STREET",
      "dest_warp_id": "17"
    }
  ],
  "coord_events": [
    {
      "type": "trigger",
      "x": 15,
      "y": 33,
      "elevation": 0,
      "var": "VAR_CASTELIA_GYM_RECEPTION_BLOCK",
      "var_value": "0",
      "script": "CasteliaCity_CasteliaGym_Eventscript_GymReceptionist_Trigger"
    },
    {
      "type": "trigger",
      "x": 16,
      "y": 33,
      "elevation": 0,
      "var": "VAR_CASTELIA_GYM_RECEPTION_BLOCK",
      "var_value": "0",
      "script": "CasteliaCity_CasteliaGym_Eventscript_GymReceptionist_Trigger"
    },
    {
      "type": "trigger",
      "x": 17,
      "y": 33,
      "elevation": 0,
      "var": "VAR_CASTELIA_GYM_RECEPTION_BLOCK",
      "var_value": "0",
      "script": "CasteliaCity_CasteliaGym_Eventscript_GymReceptionist_Trigger"
    },
    {
      "type": "trigger",
      "x": 16,
      "y": 24,
      "elevation": 0,
      "var": "VAR_CASTELIA_GYM_SWITCH_1",
      "var_value": "0",
      "script": "CasteliaCity_CasteliaGym_Eventscripy_Button1"
    },
    {
      "type": "trigger",
      "x": 28,
      "y": 24,
      "elevation": 0,
      "var": "VAR_CASTELIA_GYM_SWITCH_2",
      "var_value": "0",
      "script": "CasteliaCity_CasteliaGym_Eventscripy_Button2"
    },
    {
      "type": "trigger",
      "x": 28,
      "y": 18,
      "elevation": 0,
      "var": "VAR_CASTELIA_GYM_SWITCH_3",
      "var_value": "0",
      "script": "CasteliaCity_CasteliaGym_Eventscripy_Button3"
    },
    {
      "type": "trigger",
      "x": 16,
      "y": 18,
      "elevation": 0,
      "var": "VAR_CASTELIA_GYM_SWITCH_4",
      "var_value": "0",
      "script": "CasteliaCity_CasteliaGym_Eventscripy_Button4"
    },
    {
      "type": "trigger",
      "x": 10,
      "y": 21,
      "elevation": 0,
      "var": "VAR_CASTELIA_GYM_SWITCH_5",
      "var_value": "0",
      "script": "CasteliaCity_CasteliaGym_Eventscripy_Button5"
    },
    {
      "type": "trigger",
      "x": 22,
      "y": 15,
      "elevation": 0,
      "var": "VAR_CASTELIA_GYM_SWITCH_6",
      "var_value": "0",
      "script": "CasteliaCity_CasteliaGym_Eventscripy_Button6"
    },
    {
      "type": "trigger",
      "x": 4,
      "y": 18,
      "elevation": 0,
      "var": "VAR_CASTELIA_GYM_SWITCH_7",
      "var_value": "0",
      "script": "CasteliaCity_CasteliaGym_Eventscripy_Button7"
    },
    {
      "type": "trigger",
      "x": 10,
      "y": 15,
      "elevation": 0,
      "var": "VAR_CASTELIA_GYM_SWITCH_8",
      "var_value": "0",
      "script": "CasteliaCity_CasteliaGym_Eventscripy_Button8"
    },
    {
      "type": "trigger",
      "x": 22,
      "y": 21,
      "elevation": 0,
      "var": "VAR_CASTELIA_GYM_TRAP_1",
      "var_value": "0",
      "script": "CasteliaCity_CasteliaGym_EventScript_Battle_Harlequin_2"
    },
    {
      "type": "trigger",
      "x": 4,
      "y": 24,
      "elevation": 0,
      "var": "VAR_CASTELIA_GYM_TRAP_2",
      "var_value": "0",
      "script": "CasteliaCity_CasteliaGym_EventScript_Battle_Harlequin_3"
    }
  ],
  "bg_events": [
    {
      "type": "sign",
      "x": 13,
      "y": 35,
      "elevation": 0,
      "player_facing_dir": "BG_EVENT_PLAYER_FACING_NORTH",
      "script": "CasteliaCity_CasteliaGym_Eventscript_GymSign"
    },
    {
      "type": "sign",
      "x": 19,
      "y": 35,
      "elevation": 0,
      "player_facing_dir": "BG_EVENT_PLAYER_FACING_NORTH",
      "script": "CasteliaCity_CasteliaGym_Eventscript_GymSign"
    }
  ]
}
