{
  "id": "MAP_NIMBASA_CITY",
  "name": "NimbasaCity",
  "layout": "LAYOUT_NIMBASA_CITY",
  "music": "MUS_NIMBASA_CITY",
  "region_map_section": "MAPSEC_NIMBASA_CITY",
  "requires_flash": false,
  "weather": "WEATHER_SUNNY",
  "map_type": "MAP_TYPE_CITY",
  "allow_cycling": true,
  "allow_escaping": false,
  "allow_running": true,
  "show_map_name": true,
  "battle_scene": "MAP_BATTLE_SCENE_NORMAL",
  "connections": null,
  "object_events": [
    {
      "graphics_id": "OBJ_EVENT_GFX_PEIRRO",
      "x": 39,
      "y": 38,
      "elevation": 0,
      "movement_type": "MOVEMENT_TYPE_WANDER_AROUND",
      "movement_range_x": 1,
      "movement_range_y": 1,
      "trainer_type": "TRAINER_TYPE_NONE",
      "trainer_sight_or_berry_tree_id": "0",
      "script": "NULL",
      "flag": "0"
    },
    {
      "graphics_id": "OBJ_EVENT_GFX_ROUGHNECK",
      "x": 33,
      "y": 28,
      "elevation": 0,
      "movement_type": "MOVEMENT_TYPE_WANDER_AROUND",
      "movement_range_x": 1,
      "movement_range_y": 1,
      "trainer_type": "TRAINER_TYPE_NONE",
      "trainer_sight_or_berry_tree_id": "0",
      "script": "NULL",
      "flag": "0"
    },
    {
      "graphics_id": "OBJ_EVENT_GFX_BACKPACKER_FEMALE",
      "x": 25,
      "y": 18,
      "elevation": 0,
      "movement_type": "MOVEMENT_TYPE_WANDER_AROUND",
      "movement_range_x": 1,
      "movement_range_y": 1,
      "trainer_type": "TRAINER_TYPE_NONE",
      "trainer_sight_or_berry_tree_id": "0",
      "script": "NULL",
      "flag": "0"
    },
    {
      "graphics_id": "OBJ_EVENT_GFX_FOOTBALL_PLAYER",
      "x": 40,
      "y": 15,
      "elevation": 0,
      "movement_type": "MOVEMENT_TYPE_LOOK_AROUND",
      "movement_range_x": 0,
      "movement_range_y": 0,
      "trainer_type": "TRAINER_TYPE_NONE",
      "trainer_sight_or_berry_tree_id": "0",
      "script": "NULL",
      "flag": "0"
    },
    {
      "graphics_id": "OBJ_EVENT_GFX_BEARD_GUY",
      "x": 47,
      "y": 15,
      "elevation": 0,
      "movement_type": "MOVEMENT_TYPE_WANDER_AROUND",
      "movement_range_x": 1,
      "movement_range_y": 1,
      "trainer_type": "TRAINER_TYPE_NONE",
      "trainer_sight_or_berry_tree_id": "0",
      "script": "NULL",
      "flag": "0"
    },
    {
      "graphics_id": "OBJ_EVENT_GFX_BIANCA",
      "x": 58,
      "y": 12,
      "elevation": 0,
      "movement_type": "MOVEMENT_TYPE_FACE_UP",
      "movement_range_x": 0,
      "movement_range_y": 0,
      "trainer_type": "TRAINER_TYPE_NONE",
      "trainer_sight_or_berry_tree_id": "0",
      "script": "NULL",
      "flag": "0"
    },
    {
      "graphics_id": "OBJ_EVENT_GFX_POKEFAN_FEMALE",
      "x": 58,
      "y": 31,
      "elevation": 0,
      "movement_type": "MOVEMENT_TYPE_FACE_DOWN",
      "movement_range_x": 0,
      "movement_range_y": 0,
      "trainer_type": "TRAINER_TYPE_NONE",
      "trainer_sight_or_berry_tree_id": "0",
      "script": "NULL",
      "flag": "0"
    },
    {
      "graphics_id": "OBJ_EVENT_GFX_SCHOOL_GIRL",
      "x": 59,
      "y": 32,
      "elevation": 0,
      "movement_type": "MOVEMENT_TYPE_FACE_RIGHT",
      "movement_range_x": 0,
      "movement_range_y": 0,
      "trainer_type": "TRAINER_TYPE_NONE",
      "trainer_sight_or_berry_tree_id": "0",
      "script": "NULL",
      "flag": "0"
    },
    {
      "graphics_id": "OBJ_EVENT_GFX_GIRL_1",
      "x": 59,
      "y": 33,
      "elevation": 0,
      "movement_type": "MOVEMENT_TYPE_FACE_RIGHT",
      "movement_range_x": 0,
      "movement_range_y": 0,
      "trainer_type": "TRAINER_TYPE_NONE",
      "trainer_sight_or_berry_tree_id": "0",
      "script": "NULL",
      "flag": "0"
    },
    {
      "graphics_id": "OBJ_EVENT_GFX_GRANDPA",
      "x": 52,
      "y": 41,
      "elevation": 0,
      "movement_type": "MOVEMENT_TYPE_FACE_RIGHT",
      "movement_range_x": 0,
      "movement_range_y": 0,
      "trainer_type": "TRAINER_TYPE_NONE",
      "trainer_sight_or_berry_tree_id": "0",
      "script": "NULL",
      "flag": "0"
    },
    {
      "graphics_id": "OBJ_EVENT_GFX_PLASMA_GRUNT_MALE",
      "x": 56,
      "y": 41,
      "elevation": 0,
      "movement_type": "MOVEMENT_TYPE_FACE_LEFT",
      "movement_range_x": 0,
      "movement_range_y": 0,
      "trainer_type": "TRAINER_TYPE_NONE",
      "trainer_sight_or_berry_tree_id": "0",
      "script": "NULL",
      "flag": "0"
    },
    {
      "graphics_id": "OBJ_EVENT_GFX_PLASMA_GRUNT_MALE",
      "x": 55,
      "y": 40,
      "elevation": 0,
      "movement_type": "MOVEMENT_TYPE_FACE_LEFT",
      "movement_range_x": 0,
      "movement_range_y": 0,
      "trainer_type": "TRAINER_TYPE_NONE",
      "trainer_sight_or_berry_tree_id": "0",
      "script": "NULL",
      "flag": "0"
    },
    {
      "graphics_id": "OBJ_EVENT_GFX_ACE_TRAINER_FEMALE",
      "x": 46,
      "y": 33,
      "elevation": 0,
      "movement_type": "MOVEMENT_TYPE_FACE_DOWN",
      "movement_range_x": 0,
      "movement_range_y": 0,
      "trainer_type": "TRAINER_TYPE_NONE",
      "trainer_sight_or_berry_tree_id": "0",
      "script": "NULL",
      "flag": "FLAG_TEMPORARY_DISAPPEARING"
    }
  ],
  "warp_events": [
    {
      "x": 53,
      "y": 52,
      "elevation": 0,
      "dest_map": "MAP_ROUTE4_NORTH",
      "dest_warp_id": "0"
    },
    {
      "x": 54,
      "y": 52,
      "elevation": 0,
      "dest_map": "MAP_ROUTE4_NORTH",
      "dest_warp_id": "1"
    },
    {
      "x": 55,
      "y": 52,
      "elevation": 0,
      "dest_map": "MAP_ROUTE4_NORTH",
      "dest_warp_id": "2"
    },
    {
      "x": 30,
      "y": 40,
      "elevation": 0,
      "dest_map": "MAP_NIMBASA_CITY",
      "dest_warp_id": "0"
    },
    {
      "x": 23,
      "y": 41,
      "elevation": 0,
      "dest_map": "MAP_NIMBASA_CITY",
      "dest_warp_id": "0"
    },
    {
      "x": 23,
      "y": 31,
      "elevation": 0,
      "dest_map": "MAP_NIMBASA_CITY",
      "dest_warp_id": "0"
    },
    {
      "x": 30,
      "y": 31,
      "elevation": 0,
      "dest_map": "MAP_NIMBASA_CITY",
      "dest_warp_id": "0"
    },
    {
      "x": 46,
      "y": 33,
      "elevation": 0,
      "dest_map": "MAP_NIMBASA_CITY",
      "dest_warp_id": "0"
    },
    {
      "x": 17,
      "y": 11,
      "elevation": 0,
      "dest_map": "MAP_NIMBASA_CITY_SMALL_COURT_LOBBY",
      "dest_warp_id": "1"
    },
    {
      "x": 35,
      "y": 11,
      "elevation": 0,
      "dest_map": "MAP_NIMBASA_CITY_BIG_STADIUM_LOBBY",
      "dest_warp_id": "1"
    },
    {
      "x": 57,
      "y": 11,
      "elevation": 0,
      "dest_map": "MAP_NIMBASA_CITY_MUSICAL_THEATER",
      "dest_warp_id": "1"
    },
    {
      "x": 61,
      "y": 36,
      "elevation": 0,
      "dest_map": "MAP_NIMBASA_CITY_EXTENDED",
      "dest_warp_id": "0"
    },
    {
      "x": 61,
      "y": 37,
      "elevation": 0,
      "dest_map": "MAP_NIMBASA_CITY_EXTENDED",
      "dest_warp_id": "1"
    },
    {
      "x": 61,
      "y": 38,
      "elevation": 0,
      "dest_map": "MAP_NIMBASA_CITY_EXTENDED",
      "dest_warp_id": "2"
    },
    {
      "x": 7,
      "y": 16,
      "elevation": 0,
      "dest_map": "MAP_ROUTE5",
      "dest_warp_id": "0"
    },
    {
      "x": 7,
      "y": 17,
      "elevation": 0,
      "dest_map": "MAP_ROUTE5",
      "dest_warp_id": "1"
    },
    {
      "x": 72,
      "y": 16,
      "elevation": 0,
      "dest_map": "MAP_ROUTE16",
      "dest_warp_id": "0"
    },
    {
      "x": 72,
      "y": 17,
      "elevation": 0,
      "dest_map": "MAP_ROUTE16",
      "dest_warp_id": "1"
    }
  ],
  "coord_events": [
    {
      "type": "trigger",
      "x": 46,
      "y": 34,
      "elevation": 0,
      "var": "VAR_TEMP_0",
      "var_value": "0",
      "script": "NULL"
    }
  ],
  "bg_events": [
    {
      "type": "sign",
      "x": 11,
      "y": 13,
      "elevation": 0,
      "player_facing_dir": "BG_EVENT_PLAYER_FACING_ANY",
      "script": "NULL"
    },
    {
      "type": "sign",
      "x": 19,
      "y": 14,
      "elevation": 0,
      "player_facing_dir": "BG_EVENT_PLAYER_FACING_ANY",
      "script": "NULL"
    },
    {
      "type": "sign",
      "x": 37,
      "y": 14,
      "elevation": 0,
      "player_facing_dir": "BG_EVENT_PLAYER_FACING_ANY",
      "script": "NULL"
    },
    {
      "type": "sign",
      "x": 59,
      "y": 14,
      "elevation": 0,
      "player_facing_dir": "BG_EVENT_PLAYER_FACING_ANY",
      "script": "NULL"
    },
    {
      "type": "sign",
      "x": 68,
      "y": 13,
      "elevation": 0,
      "player_facing_dir": "BG_EVENT_PLAYER_FACING_ANY",
      "script": "NULL"
    },
    {
      "type": "sign",
      "x": 49,
      "y": 39,
      "elevation": 0,
      "player_facing_dir": "BG_EVENT_PLAYER_FACING_ANY",
      "script": "NULL"
    },
    {
      "type": "sign",
      "x": 53,
      "y": 39,
      "elevation": 0,
      "player_facing_dir": "BG_EVENT_PLAYER_FACING_ANY",
      "script": "NULL"
    },
    {
      "type": "sign",
      "x": 26,
      "y": 41,
      "elevation": 0,
      "player_facing_dir": "BG_EVENT_PLAYER_FACING_ANY",
      "script": "NULL"
    }
  ]
}
